giantmusictransformer/TMIDIX.py
giantmusictransformer/__init__.py
giantmusictransformer/giantmusictransformer.py
giantmusictransformer/midi_processors.py
giantmusictransformer/midi_to_colab_audio.py
giantmusictransformer/model_loader.py
giantmusictransformer/models.py
giantmusictransformer/sample_midis.py
giantmusictransformer/x_transformer_1_23_2.py
giantmusictransformer/examples/Giant_Music_Transformer.ipynb
giantmusictransformer/examples/Giant_Music_Transformer_Bulk_Generator.ipynb
giantmusictransformer/examples/Giant_Music_Transformer_Composer.ipynb
giantmusictransformer/examples/Giant_Music_Transformer_TTM.ipynb
giantmusictransformer/examples/README.md
giantmusictransformer/examples/__init__.py
giantmusictransformer/seed_midis/Giant-Music-Transformer-MI-Seed-1.mid
giantmusictransformer/seed_midis/Giant-Music-Transformer-MI-Seed-2.mid
giantmusictransformer/seed_midis/Giant-Music-Transformer-MI-Seed-3.mid
giantmusictransformer/seed_midis/Giant-Music-Transformer-MI-Seed-4.mid
giantmusictransformer/seed_midis/Giant-Music-Transformer-MI-Seed-5.mid
giantmusictransformer/seed_midis/Giant-Music-Transformer-MI-Seed-6.mid
giantmusictransformer/seed_midis/Giant-Music-Transformer-Piano-Seed-1.mid
giantmusictransformer/seed_midis/Giant-Music-Transformer-Piano-Seed-2.mid
giantmusictransformer/seed_midis/Giant-Music-Transformer-Piano-Seed-3.mid
giantmusictransformer/seed_midis/Giant-Music-Transformer-Piano-Seed-4.mid
giantmusictransformer/seed_midis/Giant-Music-Transformer-Piano-Seed-5.mid
giantmusictransformer/seed_midis/Giant-Music-Transformer-Piano-Seed-6.mid
giantmusictransformer/seed_midis/README.md
giantmusictransformer/seed_midis/__init__.py
giantmusictransformer-24.12.23.dist-info/LICENSE
giantmusictransformer-24.12.23.dist-info/METADATA
giantmusictransformer-24.12.23.dist-info/WHEEL
giantmusictransformer-24.12.23.dist-info/top_level.txt
giantmusictransformer-24.12.23.dist-info/RECORD
