Metadata-Version: 2.1
Name: giantmusictransformer
Version: 24.12.23
Summary: Fast multi-instrumental music transformer with true full MIDI instruments range, efficient encoding, octo-velocity and outro tokens
Home-page: https://github.com/asigalov61/giantmusictransformer
Author: Alex Lev
Author-email: Alex Lev <alexlev61@proton.me>
Maintainer-email: Alex Lev <alexlev61@proton.me>
License: Apache Software License 2.0
Project-URL: Homepage, https://github.com/asigalov61/giantmusictransformer
Project-URL: Examples, https://github.com/asigalov61/tegridymidi/giantmusictransformer/examples
Project-URL: Documentation, https://github.com/asigalov61/giantmusictransformer/docs
Project-URL: Repository, https://github.com/asigalov61/Giant-Music-Transformer
Project-URL: Issues, https://github.com/asigalov61/giantmusictransformer/issues
Project-URL: Discussions, https://github.com/asigalov61/giantmusictransformer/discussions
Project-URL: Models, https://huggingface.co/asigalov61/Giant-Music-Transformer
Project-URL: Demo, https://huggingface.co/spaces/asigalov61/Giant-Music-Transformer
Keywords: MIDI,music,music ai,music transformer,artificial instelligence
Classifier: Development Status :: 5 - Production/Stable
Classifier: Intended Audience :: Science/Research
Classifier: Topic :: Multimedia :: Sound/Audio :: MIDI
Classifier: License :: OSI Approved :: Apache Software License
Classifier: Operating System :: OS Independent
Classifier: Programming Language :: Python :: 3.6
Classifier: Programming Language :: Python :: 3.7
Classifier: Programming Language :: Python :: 3.8
Classifier: Programming Language :: Python :: 3.9
Classifier: Programming Language :: Python :: 3.10
Classifier: Programming Language :: Python :: 3.11
Classifier: Programming Language :: Python :: 3.12
Requires-Python: >=3.6
License-File: LICENSE
Requires-Dist: tqdm
Requires-Dist: ipywidgets
Requires-Dist: matplotlib
Requires-Dist: numpy
Requires-Dist: scikit-learn
Requires-Dist: torch
Requires-Dist: einops
Requires-Dist: torch-summary
Requires-Dist: hf-transfer
Requires-Dist: huggingface_hub
